azure_poetry_plugin/__init__.py
azure_poetry_plugin/plugin.py
azure_poetry_plugin-0.1.2rc0.dist-info/LICENSE
azure_poetry_plugin-0.1.2rc0.dist-info/METADATA
azure_poetry_plugin-0.1.2rc0.dist-info/WHEEL
azure_poetry_plugin-0.1.2rc0.dist-info/entry_points.txt
azure_poetry_plugin-0.1.2rc0.dist-info/RECORD
