Metadata-Version: 2.1
Name: azure-poetry-plugin
Version: 0.1.2rc0
Summary: A poetry plugin for an easy way of configuring azure artifact feeds with Poetry, without any .NET dependencies.
Author: Daniel Gottlieb Dollerup
Author-email: daniel.dollerup@gmail.com
Requires-Python: >=3.9,<4.0
Classifier: Programming Language :: Python :: 3
Classifier: Programming Language :: Python :: 3.9
Classifier: Programming Language :: Python :: 3.10
Classifier: Programming Language :: Python :: 3.11
Classifier: Programming Language :: Python :: 3.12
Requires-Dist: nox-poetry (>=1.0.3,<2.0.0)
Requires-Dist: poetry (>=1.8.3,<2.0.0)
